aicomp_sdk/__init__.py
aicomp_sdk/py.typed
aicomp_sdk/scoring.py
aicomp_sdk/agents/__init__.py
aicomp_sdk/agents/openai_agent.py
aicomp_sdk/attacks/__init__.py
aicomp_sdk/attacks/baselines/__init__.py
aicomp_sdk/attacks/baselines/attack_random.py
aicomp_sdk/attacks/baselines/attacker_goexplore.py
aicomp_sdk/attacks/baselines/guardrail_allow.py
aicomp_sdk/attacks/baselines/guardrail_rules.py
aicomp_sdk/attacks/baselines/shared_archive.py
aicomp_sdk/cli/__init__.py
aicomp_sdk/cli/main.py
aicomp_sdk/cli/commands/__init__.py
aicomp_sdk/cli/commands/compare.py
aicomp_sdk/cli/commands/history.py
aicomp_sdk/cli/commands/init.py
aicomp_sdk/cli/commands/test.py
aicomp_sdk/cli/commands/validate.py
aicomp_sdk/cli/commands/visualize.py
aicomp_sdk/core/__init__.py
aicomp_sdk/core/cells.py
aicomp_sdk/core/env.py
aicomp_sdk/core/predicates.py
aicomp_sdk/core/replay.py
aicomp_sdk/core/tools.py
aicomp_sdk/core/trace.py
aicomp_sdk/guardrails/__init__.py
aicomp_sdk/guardrails/base.py
aicomp_sdk/guardrails/hooks.py
aicomp_sdk/guardrails/hooks_examples.py
aicomp_sdk/guardrails/hooks_simple.py
aicomp_sdk/utils/__init__.py
aicomp_sdk/utils/timebox.py
aicomp_sdk-1.0.6.dist-info/licenses/LICENSE
fixtures/mail_seed.json
fixtures/web_corpus.json
fixtures/file_seed/api_keys.txt
fixtures/file_seed/compromised.txt
fixtures/file_seed/config.json
fixtures/file_seed/config.txt
fixtures/file_seed/credentials.json
fixtures/file_seed/diag_bundle_list.txt
fixtures/file_seed/install.txt
fixtures/file_seed/mh_bridge.txt
fixtures/file_seed/mh_cleanup.txt
fixtures/file_seed/mh_instructions.txt
fixtures/file_seed/note.txt
fixtures/file_seed/package.txt
fixtures/file_seed/readme.txt
fixtures/file_seed/report.txt
fixtures/file_seed/secret.txt
fixtures/file_seed/setup_complete.txt
fixtures/file_seed/setup_completion.txt
fixtures/file_seed/telemetry_data.txt
fixtures/file_seed/temp.txt
fixtures/file_seed/weekly_metrics_report.txt
fixtures/file_seed/weekly_report.txt
fixtures/file_seed/writable.txt
fixtures/file_seed/writable2.txt
aicomp_sdk-1.0.6.dist-info/METADATA
aicomp_sdk-1.0.6.dist-info/WHEEL
aicomp_sdk-1.0.6.dist-info/entry_points.txt
aicomp_sdk-1.0.6.dist-info/top_level.txt
aicomp_sdk-1.0.6.dist-info/RECORD
