Metadata-Version: 2.4
Name: aicomp-sdk
Version: 1.0.6
Summary: AI Agent Security Competition SDK - Red teaming framework for tool-using AI agents
Home-page: https://github.com/mbhatt1/competitionscratch
Author: Competition Organizers
Author-email: 
License: MIT
Project-URL: Homepage, https://github.com/mbhatt1/competitionscratch
Project-URL: Documentation, https://github.com/mbhatt1/competitionscratch/blob/main/docs/README.md
Project-URL: Repository, https://github.com/mbhatt1/competitionscratch
Project-URL: Bug Tracker, https://github.com/mbhatt1/competitionscratch/issues
Keywords: ai,security,red-team,guardrails,llm,agent-safety,adversarial-ml
Classifier: Development Status :: 4 - Beta
Classifier: Intended Audience :: Developers
Classifier: Intended Audience :: Science/Research
Classifier: Intended Audience :: Education
Classifier: Topic :: Scientific/Engineering :: Artificial Intelligence
Classifier: Topic :: Security
Classifier: Topic :: Software Development :: Testing
Classifier: License :: OSI Approved :: MIT License
Classifier: Programming Language :: Python :: 3
Classifier: Programming Language :: Python :: 3.8
Classifier: Programming Language :: Python :: 3.9
Classifier: Programming Language :: Python :: 3.10
Classifier: Programming Language :: Python :: 3.11
Classifier: Programming Language :: Python :: 3.12
Classifier: Operating System :: OS Independent
Classifier: Typing :: Typed
Requires-Python: >=3.8
License-File: LICENSE
Requires-Dist: transformers>=4.30.0
Requires-Dist: torch>=2.0.0
Requires-Dist: openai>=1.0.0
Provides-Extra: dev
Requires-Dist: pytest>=7.0.0; extra == "dev"
Requires-Dist: pytest-cov>=4.0.0; extra == "dev"
Requires-Dist: black>=23.0.0; extra == "dev"
Requires-Dist: flake8>=6.0.0; extra == "dev"
Requires-Dist: isort>=5.12.0; extra == "dev"
Requires-Dist: mypy>=1.0.0; extra == "dev"
Provides-Extra: docs
Requires-Dist: sphinx>=6.0.0; extra == "docs"
Requires-Dist: sphinx-rtd-theme>=1.2.0; extra == "docs"
Dynamic: home-page
Dynamic: license-file
Dynamic: requires-python
